{"indexes":[{"v":{"$numberInt":"2"},"key":{"_id":{"$numberInt":"1"}},"name":"_id_"},{"v":{"$numberInt":"2"},"key":{"_appointmentRef":{"$numberInt":"1"}},"name":"_appointmentRef_1","background":true},{"v":{"$numberInt":"2"},"unique":true,"key":{"formKey":{"$numberInt":"1"}},"name":"formKey_1","background":true},{"v":{"$numberInt":"2"},"key":{"originalFormDetails._id":{"$numberInt":"1"}},"name":"originalFormDetails._id_1","background":true},{"v":{"$numberInt":"2"},"key":{"originalFormDetails.formKey":{"$numberInt":"1"}},"name":"originalFormDetails.formKey_1","background":true}],"uuid":"9648170ad61c4e5684ecd1f9f4ffd4c8","collectionName":"forms","type":"collection"}